treepath/__init__.py
treepath/descriptor/__init__.py
treepath/descriptor/abstract_document.py
treepath/descriptor/descriptor_builder.py
treepath/descriptor/descriptor_functions.py
treepath/descriptor/document.py
treepath/descriptor/document_iterator.py
treepath/descriptor/document_list.py
treepath/descriptor/path_descriptor.py
treepath/path/__init__.py
treepath/path/builder/__init__.py
treepath/path/builder/abstract_class_builder.py
treepath/path/builder/dash_path_builder.py
treepath/path/builder/patch_constants.py
treepath/path/builder/path_builder.py
treepath/path/builder/path_builder_predicate.py
treepath/path/builder/path_predicate.py
treepath/path/builder/root_path_builder.py
treepath/path/builder/symbol.py
treepath/path/exceptions/__init__.py
treepath/path/exceptions/infinite_loop_detected.py
treepath/path/exceptions/match_not_found_error.py
treepath/path/exceptions/nested_match_not_found_error.py
treepath/path/exceptions/path_syntax_error.py
treepath/path/exceptions/pop_error.py
treepath/path/exceptions/set_error.py
treepath/path/exceptions/stop_traversing.py
treepath/path/exceptions/traversing_error.py
treepath/path/exceptions/treepath_exception.py
treepath/path/traverser/__init__.py
treepath/path/traverser/has_function.py
treepath/path/traverser/imaginary_match.py
treepath/path/traverser/key_match.py
treepath/path/traverser/list_match.py
treepath/path/traverser/match.py
treepath/path/traverser/match_traverser.py
treepath/path/traverser/nested_match_traverser.py
treepath/path/traverser/nested_value_traverser.py
treepath/path/traverser/parent_match.py
treepath/path/traverser/predicate_match.py
treepath/path/traverser/root_match.py
treepath/path/traverser/trace.py
treepath/path/traverser/traverser_functions.py
treepath/path/traverser/traverser_match.py
treepath/path/traverser/value_traverser.py
treepath/path/typing/__init__.py
treepath/path/typing/json_arg_types.py
treepath/path/typing/json_types.py
treepath/path/utils/__init__.py
treepath-3.0.2.dist-info/LICENSE.md
treepath-3.0.2.dist-info/METADATA
treepath-3.0.2.dist-info/WHEEL
treepath-3.0.2.dist-info/top_level.txt
treepath-3.0.2.dist-info/RECORD
