Metadata-Version: 2.2
Name: treepath
Version: 3.0.2
Summary: A python query language, similar to xpath and jsonpath, for extracting data from a json data structure.
Author-email: Joey Sullivan <monkeydevtools@gmail.com>
Maintainer-email: Joey Sullivan <monkeydevtools@gmail.com>
License:                                  Apache License
Project-URL: Repository, https://github.com/monkeydevtools/treepath-python
Classifier: Programming Language :: Python :: 3.9
Classifier: Programming Language :: Python :: 3.10
Classifier: Programming Language :: Python :: 3.11
Classifier: Programming Language :: Python :: 3.12
Classifier: Programming Language :: Python :: 3.13
Classifier: License :: OSI Approved :: Apache Software License
Classifier: Operating System :: OS Independent
Requires-Python: >=3.9
License-File: LICENSE.md
Provides-Extra: test
Requires-Dist: pytest; extra == "test"
Requires-Dist: pytest-cov; extra == "test"
Requires-Dist: tox; extra == "test"
